fsoft_maid.py
lib/__init__.py
lib/pattern_matcher.py
fsoft_maid-0.4.7.dist-info/LICENSE
fsoft_maid-0.4.7.dist-info/METADATA
fsoft_maid-0.4.7.dist-info/WHEEL
fsoft_maid-0.4.7.dist-info/entry_points.txt
fsoft_maid-0.4.7.dist-info/top_level.txt
fsoft_maid-0.4.7.dist-info/RECORD
