Metadata-Version: 2.1
Name: fsoft-maid
Version: 0.4.7
Summary: Markdown AI Doc creator
Home-page: https://github.com/fsoft72/maid
Author: Fabio Rotondo
Author-email: fsoft.devel@gmail.com
License: MIT
Classifier: Programming Language :: Python :: 3
Classifier: License :: OSI Approved :: MIT License
Classifier: Operating System :: OS Independent
Requires-Python: >=3.6
License-File: LICENSE
